masquer/__about__.py
masquer/__init__.py
masquer/app.py
masquer/utils/__init__.py
masquer/utils/assets.py
masquer/utils/response.py
masquer/utils/select.py
masquer/utils/validate.py
masquer-1.3.5.dist-info/METADATA
masquer-1.3.5.dist-info/WHEEL
masquer-1.3.5.dist-info/licenses/LICENSE
masquer-1.3.5.dist-info/RECORD
