Metadata-Version: 2.3
Name: masquer
Version: 1.3.5
Summary: A tool to generate random user-agent and referer data for HTTP requests
Project-URL: documentation, https://github.com/essteer/masquer/blob/main/README.md
Project-URL: repository, https://github.com/essteer/masquer
Project-URL: issues, https://github.com/essteer/masquer/issues
Project-URL: docker, https://hub.docker.com/r/essteer/masquer
Author-email: Elliott Steer <essteer@pm.me>
License: MIT License
License-File: LICENSE
Keywords: header data,requests,user-agents
Classifier: Development Status :: 5 - Production/Stable
Classifier: Intended Audience :: Developers
Classifier: License :: OSI Approved :: MIT License
Classifier: Natural Language :: English
Classifier: Operating System :: OS Independent
Classifier: Programming Language :: Python :: 3
Classifier: Programming Language :: Python :: 3.9
Classifier: Programming Language :: Python :: 3.10
Classifier: Programming Language :: Python :: 3.11
Classifier: Programming Language :: Python :: 3.12
Classifier: Programming Language :: Python :: 3.13
Requires-Python: >=3.9
Provides-Extra: extras
Requires-Dist: beautifulsoup4==4.12.3; extra == 'extras'
Requires-Dist: fastapi==0.111.0; extra == 'extras'
